easypv/__init__.py
easypv/adrmdr.py
easypv/adrmdr.pyd
easypv/easypv.py
easypv/easypv.pyd
easypv/easystat.py
easypv/easystat.pyd
easypv/pinggutools.py
easypv/pinggutools.pyd
easypv/ver.py
easypv/data/def.zip
easypv/data/sor.zip
easypv/data/version.txt
easypv-3.9.0.dist-info/LICENSE
easypv-3.9.0.dist-info/METADATA
easypv-3.9.0.dist-info/WHEEL
easypv-3.9.0.dist-info/entry_points.txt
easypv-3.9.0.dist-info/top_level.txt
easypv-3.9.0.dist-info/RECORD
