Metadata-Version: 2.1
Name: easypv
Version: 3.9.0
Summary: EasyPV is a Python tool designed for statistical analysis.
Author: sysucai
Author-email: 411703730@qq.com
Platform: Windows
Classifier: Programming Language :: Python :: 3
Classifier: License :: OSI Approved :: MIT License
Classifier: Operating System :: Microsoft :: Windows
Requires-Python: >=3.8
License-File: LICENSE
Requires-Dist: pandas>=1.3.4
Requires-Dist: numpy>=1.21.3
Requires-Dist: xlrd>=1.2.0
Requires-Dist: xlwt>=1.3.0
Requires-Dist: openpyxl>=3.0.9
Requires-Dist: xlsxwriter>=3.0.1
Requires-Dist: matplotlib>=3.4.3
Requires-Dist: requests>=2.28.1
Requires-Dist: sqlalchemy>=2.0.22
Requires-Dist: scipy>=0.7.0
Requires-Dist: seaborn>=0.11.0
Requires-Dist: python-docx>=1.1.0
Requires-Dist: scikit-learn>=0.0.1
Requires-Dist: pycryptodome>=0.0.1
Requires-Dist: statsmodels>=0.0.1
Requires-Dist: packaging>=24.0
Requires-Dist: easypymanager>=0.0.1
